{"currency": "BTC", "price_usd": 95976.0, "timestamp": 1746271277.0572195}
{"currency": "BTC", "price_usd": 95986.0, "timestamp": 1746271337.418869}
{"currency": "BTC", "price_usd": 95998.0, "timestamp": 1746271397.7646096}
{"currency": "BTC", "price_usd": 96008.0, "timestamp": 1746271458.116418}
{"currency": "BTC", "price_usd": 96017.0, "timestamp": 1746271518.488286}
{"currency": "BTC", "price_usd": 96021.0, "timestamp": 1746271578.852314}
{"currency": "BTC", "price_usd": 96028.0, "timestamp": 1746271639.3294704}
{"currency": "BTC", "price_usd": 96026.0, "timestamp": 1746271699.6838694}
{"currency": "BTC", "price_usd": 96025.0, "timestamp": 1746271760.0430102}
{"currency": "BTC", "price_usd": 96030.0, "timestamp": 1746271820.4343917}
{"currency": "BTC", "price_usd": 96035.0, "timestamp": 1746271880.7657154}
{"currency": "BTC", "price_usd": 96032.0, "timestamp": 1746271941.2436697}
{"currency": "BTC", "price_usd": 96025.0, "timestamp": 1746272004.2075455}
{"currency": "BTC", "price_usd": 96022.0, "timestamp": 1746272062.928667}
{"currency": "BTC", "price_usd": 96035.0, "timestamp": 1746272123.3066244}
{"currency": "BTC", "price_usd": 96048.0, "timestamp": 1746272183.6783657}
{"currency": "BTC", "price_usd": 96050.0, "timestamp": 1746272244.0365038}
{"currency": "BTC", "price_usd": 96060.0, "timestamp": 1746272304.3985708}
{"currency": "BTC", "price_usd": 96072.0, "timestamp": 1746272364.7761288}
{"currency": "BTC", "price_usd": 96068.0, "timestamp": 1746272425.1308708}
{"currency": "BTC", "price_usd": 96075.0, "timestamp": 1746272485.473418}
{"currency": "BTC", "price_usd": 96063.0, "timestamp": 1746272545.8507106}
{"currency": "BTC", "price_usd": 96051.0, "timestamp": 1746272606.1669989}
{"currency": "BTC", "price_usd": 96033.0, "timestamp": 1746272666.500974}
{"currency": "BTC", "price_usd": 96016.0, "timestamp": 1746272726.8572571}
{"currency": "BTC", "price_usd": 96008.0, "timestamp": 1746272787.184676}
{"currency": "BTC", "price_usd": 96001.0, "timestamp": 1746272847.545025}
{"currency": "BTC", "price_usd": 95985.0, "timestamp": 1746272907.8955288}
{"currency": "BTC", "price_usd": 95976.0, "timestamp": 1746272968.239694}
{"currency": "BTC", "price_usd": 95964.0, "timestamp": 1746273028.5822368}
{"currency": "BTC", "price_usd": 95969.0, "timestamp": 1746273088.9654877}
{"currency": "BTC", "price_usd": 95974.0, "timestamp": 1746273149.3485801}
{"currency": "BTC", "price_usd": 95979.0, "timestamp": 1746273209.6896193}
{"currency": "BTC", "price_usd": 95983.0, "timestamp": 1746273270.03875}
{"currency": "BTC", "price_usd": 95993.0, "timestamp": 1746273330.390575}
{"currency": "BTC", "price_usd": 95985.0, "timestamp": 1746273390.7645419}
{"currency": "BTC", "price_usd": 95973.0, "timestamp": 1746273451.1217182}
{"currency": "BTC", "price_usd": 95963.0, "timestamp": 1746273511.4869287}
{"currency": "BTC", "price_usd": 95958.0, "timestamp": 1746273571.8742409}
{"currency": "BTC", "price_usd": 95959.0, "timestamp": 1746273632.207562}
{"currency": "BTC", "price_usd": 95965.0, "timestamp": 1746273692.591766}
{"currency": "BTC", "price_usd": 95974.0, "timestamp": 1746273752.9663982}
{"currency": "BTC", "price_usd": 95980.0, "timestamp": 1746273813.3227835}
{"currency": "BTC", "price_usd": 95980.0, "timestamp": 1746273873.701799}
{"currency": "BTC", "price_usd": 95982.0, "timestamp": 1746273934.0770745}
{"currency": "BTC", "price_usd": 95982.0, "timestamp": 1746273994.4534898}
{"currency": "BTC", "price_usd": 95964.0, "timestamp": 1746274054.7973022}
{"currency": "BTC", "price_usd": 95951.0, "timestamp": 1746274115.1275256}
{"currency": "BTC", "price_usd": 95945.0, "timestamp": 1746274175.4908404}
{"currency": "BTC", "price_usd": 95943.0, "timestamp": 1746274235.8513646}